{"proprietary_id": "irus:8892521", "URI": null, "DOI": "17.94184/192.9617439216201", "ISBN": "111", "book_title": "Worker laugh style meeting.", "grant": "grant", "grant_number": "grant number", "publisher": "Publisher Name", "begin_date": "2021-02-01", "end_date": "2021-02-28", "title_requests": 16, "total_item_investigations": null, "total_item_requests": null, "unique_item_investigations": null, "unique_item_requests": null, "country": [{"name": "Argentina", "code": "AR", "title_requests": null, "total_item_investigations": 2, "total_item_requests": 2, "unique_item_investigations": 2, "unique_item_requests": 2}, {"name": "Belgium", "code": "BE", "title_requests": null, "total_item_investigations": 1, "total_item_requests": 1, "unique_item_investigations": 1, "unique_item_requests": 1}, {"name": "Germany", "code": "DE", "title_requests": null, "total_item_investigations": 1, "total_item_requests": 1, "unique_item_investigations": 1, "unique_item_requests": 1}, {"name": "United Kingdom", "code": "GB", "title_requests": null, "total_item_investigations": 4, "total_item_requests": 4, "unique_item_investigations": 2, "unique_item_requests": 2}, {"name": "India", "code": "IN", "title_requests": null, "total_item_investigations": 1, "total_item_requests": 1, "unique_item_investigations": 1, "unique_item_requests": 1}, {"name": "Italy", "code": "IT", "title_requests": null, "total_item_investigations": 2, "total_item_requests": 2, "unique_item_investigations": 2, "unique_item_requests": 2}, {"name": "Philippines", "code": "PH", "title_requests": null, "total_item_investigations": 2, "total_item_requests": 2, "unique_item_investigations": 2, "unique_item_requests": 2}, {"name": "Taiwan", "code": "TW", "title_requests": null, "total_item_investigations": 1, "total_item_requests": 1, "unique_item_investigations": 1, "unique_item_requests": 1}, {"name": "United States", "code": "US", "title_requests": null, "total_item_investigations": 2, "total_item_requests": 2, "unique_item_investigations": 2, "unique_item_requests": 2}], "locations": [{"latitude": 14.6476, "longitude": 121.0494, "city": "Quezon City", "country_name": "Philippines", "country_code": "PH", "title_requests": null, "total_item_investigations": 1, "total_item_requests": 1, "unique_item_investigations": 1, "unique_item_requests": 1}, {"latitude": 14.7344, "longitude": 121.1425, "city": "Rodriguez", "country_name": "Philippines", "country_code": "PH", "title_requests": null, "total_item_investigations": 1, "total_item_requests": 1, "unique_item_investigations": 1, "unique_item_requests": 1}, {"latitude": 24.144, "longitude": 120.6844, "city": "Taichung", "country_name": "Taiwan", "country_code": "TW", "title_requests": null, "total_item_investigations": 1, "total_item_requests": 1, "unique_item_investigations": 1, "unique_item_requests": 1}, {"latitude": 37.7562, "longitude": -122.4866, "city": "San Francisco", "country_name": "United States", "country_code": "US", "title_requests": null, "total_item_investigations": 1, "total_item_requests": 1, "unique_item_investigations": 1, "unique_item_requests": 1}, {"latitude": 53.8554, "longitude": -1.5492, "city": "Leeds", "country_name": "United Kingdom", "country_code": "GB", "title_requests": null, "total_item_investigations": 4, "total_item_requests": 4, "unique_item_investigations": 2, "unique_item_requests": 2}, {"latitude": -34.5705, "longitude": -58.6269, "city": "Hurlingham", "country_name": "Argentina", "country_code": "AR", "title_requests": null, "total_item_investigations": 1, "total_item_requests": 1, "unique_item_investigations": 1, "unique_item_requests": 1}, {"latitude": -26.3975, "longitude": -54.6305, "city": "Puerto Eldorado", "country_name": "Argentina", "country_code": "AR", "title_requests": null, "total_item_investigations": 1, "total_item_requests": 1, "unique_item_investigations": 1, "unique_item_requests": 1}, {"latitude": 26.8756, "longitude": 80.9115, "city": "Lucknow", "country_name": "India", "country_code": "IN", "title_requests": null, "total_item_investigations": 1, "total_item_requests": 1, "unique_item_investigations": 1, "unique_item_requests": 1}, {"latitude": 32.1453, "longitude": -110.9456, "city": "Tucson", "country_name": "United States", "country_code": "US", "title_requests": null, "total_item_investigations": 1, "total_item_requests": 1, "unique_item_investigations": 1, "unique_item_requests": 1}, {"latitude": 46.1385, "longitude": 13.2226, "city": "Reana del Rojale", "country_name": "Italy", "country_code": "IT", "title_requests": null, "total_item_investigations": 1, "total_item_requests": 1, "unique_item_investigations": 1, "unique_item_requests": 1}, {"latitude": 50.406, "longitude": 4.4842, "city": "Montignies-sur-Sambre", "country_name": "Belgium", "country_code": "BE", "title_requests": null, "total_item_investigations": 1, "total_item_requests": 1, "unique_item_investigations": 1, "unique_item_requests": 1}, {"latitude": 43.4631, "longitude": 11.8783, "city": "Arezzo", "country_name": "Italy", "country_code": "IT", "title_requests": null, "total_item_investigations": 1, "total_item_requests": 1, "unique_item_investigations": 1, "unique_item_requests": 1}, {"latitude": 51.3235, "longitude": 12.4266, "city": "Leipzig", "country_name": "Germany", "country_code": "DE", "title_requests": null, "total_item_investigations": 1, "total_item_requests": 1, "unique_item_investigations": 1, "unique_item_requests": 1}], "version": "5", "release_date": "2021-01-01"}
{"proprietary_id": "irus:8892521", "URI": null, "DOI": "17.94184/192.9617439216201", "ISBN": "112", "book_title": "Worker laugh style meeting.", "grant": "grant", "grant_number": "grant number", "publisher": "Publisher Name", "begin_date": "2021-02-01", "end_date": "2021-02-28", "title_requests": 16, "total_item_investigations": null, "total_item_requests": null, "unique_item_investigations": null, "unique_item_requests": null, "country": [{"name": "Argentina", "code": "AR", "title_requests": null, "total_item_investigations": 2, "total_item_requests": 2, "unique_item_investigations": 2, "unique_item_requests": 2}, {"name": "Belgium", "code": "BE", "title_requests": null, "total_item_investigations": 1, "total_item_requests": 1, "unique_item_investigations": 1, "unique_item_requests": 1}, {"name": "Germany", "code": "DE", "title_requests": null, "total_item_investigations": 1, "total_item_requests": 1, "unique_item_investigations": 1, "unique_item_requests": 1}, {"name": "United Kingdom", "code": "GB", "title_requests": null, "total_item_investigations": 4, "total_item_requests": 4, "unique_item_investigations": 2, "unique_item_requests": 2}, {"name": "India", "code": "IN", "title_requests": null, "total_item_investigations": 1, "total_item_requests": 1, "unique_item_investigations": 1, "unique_item_requests": 1}, {"name": "Italy", "code": "IT", "title_requests": null, "total_item_investigations": 2, "total_item_requests": 2, "unique_item_investigations": 2, "unique_item_requests": 2}, {"name": "Philippines", "code": "PH", "title_requests": null, "total_item_investigations": 2, "total_item_requests": 2, "unique_item_investigations": 2, "unique_item_requests": 2}, {"name": "Taiwan", "code": "TW", "title_requests": null, "total_item_investigations": 1, "total_item_requests": 1, "unique_item_investigations": 1, "unique_item_requests": 1}, {"name": "United States", "code": "US", "title_requests": null, "total_item_investigations": 2, "total_item_requests": 2, "unique_item_investigations": 2, "unique_item_requests": 2}], "locations": [{"latitude": 14.6476, "longitude": 121.0494, "city": "Quezon City", "country_name": "Philippines", "country_code": "PH", "title_requests": null, "total_item_investigations": 1, "total_item_requests": 1, "unique_item_investigations": 1, "unique_item_requests": 1}, {"latitude": 14.7344, "longitude": 121.1425, "city": "Rodriguez", "country_name": "Philippines", "country_code": "PH", "title_requests": null, "total_item_investigations": 1, "total_item_requests": 1, "unique_item_investigations": 1, "unique_item_requests": 1}, {"latitude": 24.144, "longitude": 120.6844, "city": "Taichung", "country_name": "Taiwan", "country_code": "TW", "title_requests": null, "total_item_investigations": 1, "total_item_requests": 1, "unique_item_investigations": 1, "unique_item_requests": 1}, {"latitude": 37.7562, "longitude": -122.4866, "city": "San Francisco", "country_name": "United States", "country_code": "US", "title_requests": null, "total_item_investigations": 1, "total_item_requests": 1, "unique_item_investigations": 1, "unique_item_requests": 1}, {"latitude": 53.8554, "longitude": -1.5492, "city": "Leeds", "country_name": "United Kingdom", "country_code": "GB", "title_requests": null, "total_item_investigations": 4, "total_item_requests": 4, "unique_item_investigations": 2, "unique_item_requests": 2}, {"latitude": -34.5705, "longitude": -58.6269, "city": "Hurlingham", "country_name": "Argentina", "country_code": "AR", "title_requests": null, "total_item_investigations": 1, "total_item_requests": 1, "unique_item_investigations": 1, "unique_item_requests": 1}, {"latitude": -26.3975, "longitude": -54.6305, "city": "Puerto Eldorado", "country_name": "Argentina", "country_code": "AR", "title_requests": null, "total_item_investigations": 1, "total_item_requests": 1, "unique_item_investigations": 1, "unique_item_requests": 1}, {"latitude": 26.8756, "longitude": 80.9115, "city": "Lucknow", "country_name": "India", "country_code": "IN", "title_requests": null, "total_item_investigations": 1, "total_item_requests": 1, "unique_item_investigations": 1, "unique_item_requests": 1}, {"latitude": 32.1453, "longitude": -110.9456, "city": "Tucson", "country_name": "United States", "country_code": "US", "title_requests": null, "total_item_investigations": 1, "total_item_requests": 1, "unique_item_investigations": 1, "unique_item_requests": 1}, {"latitude": 46.1385, "longitude": 13.2226, "city": "Reana del Rojale", "country_name": "Italy", "country_code": "IT", "title_requests": null, "total_item_investigations": 1, "total_item_requests": 1, "unique_item_investigations": 1, "unique_item_requests": 1}, {"latitude": 50.406, "longitude": 4.4842, "city": "Montignies-sur-Sambre", "country_name": "Belgium", "country_code": "BE", "title_requests": null, "total_item_investigations": 1, "total_item_requests": 1, "unique_item_investigations": 1, "unique_item_requests": 1}, {"latitude": 43.4631, "longitude": 11.8783, "city": "Arezzo", "country_name": "Italy", "country_code": "IT", "title_requests": null, "total_item_investigations": 1, "total_item_requests": 1, "unique_item_investigations": 1, "unique_item_requests": 1}, {"latitude": 51.3235, "longitude": 12.4266, "city": "Leipzig", "country_name": "Germany", "country_code": "DE", "title_requests": null, "total_item_investigations": 1, "total_item_requests": 1, "unique_item_investigations": 1, "unique_item_requests": 1}], "version": "5", "release_date": "2021-01-01"}
{"proprietary_id": "irus:8892521", "URI": null, "DOI": "17.94184/192.9617439216201", "ISBN": "113", "book_title": "Worker laugh style meeting.", "grant": "grant", "grant_number": "grant number", "publisher": "Publisher Name", "begin_date": "2021-02-01", "end_date": "2021-02-28", "title_requests": 16, "total_item_investigations": null, "total_item_requests": null, "unique_item_investigations": null, "unique_item_requests": null, "country": [{"name": "Argentina", "code": "AR", "title_requests": null, "total_item_investigations": 2, "total_item_requests": 2, "unique_item_investigations": 2, "unique_item_requests": 2}, {"name": "Belgium", "code": "BE", "title_requests": null, "total_item_investigations": 1, "total_item_requests": 1, "unique_item_investigations": 1, "unique_item_requests": 1}, {"name": "Germany", "code": "DE", "title_requests": null, "total_item_investigations": 1, "total_item_requests": 1, "unique_item_investigations": 1, "unique_item_requests": 1}, {"name": "United Kingdom", "code": "GB", "title_requests": null, "total_item_investigations": 4, "total_item_requests": 4, "unique_item_investigations": 2, "unique_item_requests": 2}, {"name": "India", "code": "IN", "title_requests": null, "total_item_investigations": 1, "total_item_requests": 1, "unique_item_investigations": 1, "unique_item_requests": 1}, {"name": "Italy", "code": "IT", "title_requests": null, "total_item_investigations": 2, "total_item_requests": 2, "unique_item_investigations": 2, "unique_item_requests": 2}, {"name": "Philippines", "code": "PH", "title_requests": null, "total_item_investigations": 2, "total_item_requests": 2, "unique_item_investigations": 2, "unique_item_requests": 2}, {"name": "Taiwan", "code": "TW", "title_requests": null, "total_item_investigations": 1, "total_item_requests": 1, "unique_item_investigations": 1, "unique_item_requests": 1}, {"name": "United States", "code": "US", "title_requests": null, "total_item_investigations": 2, "total_item_requests": 2, "unique_item_investigations": 2, "unique_item_requests": 2}], "locations": [{"latitude": 14.6476, "longitude": 121.0494, "city": "Quezon City", "country_name": "Philippines", "country_code": "PH", "title_requests": null, "total_item_investigations": 1, "total_item_requests": 1, "unique_item_investigations": 1, "unique_item_requests": 1}, {"latitude": 14.7344, "longitude": 121.1425, "city": "Rodriguez", "country_name": "Philippines", "country_code": "PH", "title_requests": null, "total_item_investigations": 1, "total_item_requests": 1, "unique_item_investigations": 1, "unique_item_requests": 1}, {"latitude": 24.144, "longitude": 120.6844, "city": "Taichung", "country_name": "Taiwan", "country_code": "TW", "title_requests": null, "total_item_investigations": 1, "total_item_requests": 1, "unique_item_investigations": 1, "unique_item_requests": 1}, {"latitude": 37.7562, "longitude": -122.4866, "city": "San Francisco", "country_name": "United States", "country_code": "US", "title_requests": null, "total_item_investigations": 1, "total_item_requests": 1, "unique_item_investigations": 1, "unique_item_requests": 1}, {"latitude": 53.8554, "longitude": -1.5492, "city": "Leeds", "country_name": "United Kingdom", "country_code": "GB", "title_requests": null, "total_item_investigations": 4, "total_item_requests": 4, "unique_item_investigations": 2, "unique_item_requests": 2}, {"latitude": -34.5705, "longitude": -58.6269, "city": "Hurlingham", "country_name": "Argentina", "country_code": "AR", "title_requests": null, "total_item_investigations": 1, "total_item_requests": 1, "unique_item_investigations": 1, "unique_item_requests": 1}, {"latitude": -26.3975, "longitude": -54.6305, "city": "Puerto Eldorado", "country_name": "Argentina", "country_code": "AR", "title_requests": null, "total_item_investigations": 1, "total_item_requests": 1, "unique_item_investigations": 1, "unique_item_requests": 1}, {"latitude": 26.8756, "longitude": 80.9115, "city": "Lucknow", "country_name": "India", "country_code": "IN", "title_requests": null, "total_item_investigations": 1, "total_item_requests": 1, "unique_item_investigations": 1, "unique_item_requests": 1}, {"latitude": 32.1453, "longitude": -110.9456, "city": "Tucson", "country_name": "United States", "country_code": "US", "title_requests": null, "total_item_investigations": 1, "total_item_requests": 1, "unique_item_investigations": 1, "unique_item_requests": 1}, {"latitude": 46.1385, "longitude": 13.2226, "city": "Reana del Rojale", "country_name": "Italy", "country_code": "IT", "title_requests": null, "total_item_investigations": 1, "total_item_requests": 1, "unique_item_investigations": 1, "unique_item_requests": 1}, {"latitude": 50.406, "longitude": 4.4842, "city": "Montignies-sur-Sambre", "country_name": "Belgium", "country_code": "BE", "title_requests": null, "total_item_investigations": 1, "total_item_requests": 1, "unique_item_investigations": 1, "unique_item_requests": 1}, {"latitude": 43.4631, "longitude": 11.8783, "city": "Arezzo", "country_name": "Italy", "country_code": "IT", "title_requests": null, "total_item_investigations": 1, "total_item_requests": 1, "unique_item_investigations": 1, "unique_item_requests": 1}, {"latitude": 51.3235, "longitude": 12.4266, "city": "Leipzig", "country_name": "Germany", "country_code": "DE", "title_requests": null, "total_item_investigations": 1, "total_item_requests": 1, "unique_item_investigations": 1, "unique_item_requests": 1}], "version": "5", "release_date": "2021-01-01"}
{"proprietary_id": "irus:8892521", "URI": null, "DOI": "17.94184/192.9617439216201", "ISBN": "211", "book_title": "Worker laugh style meeting.", "grant": "grant", "grant_number": "grant number", "publisher": "Publisher Name", "begin_date": "2021-02-01", "end_date": "2021-02-28", "title_requests": 16, "total_item_investigations": null, "total_item_requests": null, "unique_item_investigations": null, "unique_item_requests": null, "country": [{"name": "Argentina", "code": "AR", "title_requests": null, "total_item_investigations": 2, "total_item_requests": 2, "unique_item_investigations": 2, "unique_item_requests": 2}, {"name": "Belgium", "code": "BE", "title_requests": null, "total_item_investigations": 1, "total_item_requests": 1, "unique_item_investigations": 1, "unique_item_requests": 1}, {"name": "Germany", "code": "DE", "title_requests": null, "total_item_investigations": 1, "total_item_requests": 1, "unique_item_investigations": 1, "unique_item_requests": 1}, {"name": "United Kingdom", "code": "GB", "title_requests": null, "total_item_investigations": 4, "total_item_requests": 4, "unique_item_investigations": 2, "unique_item_requests": 2}, {"name": "India", "code": "IN", "title_requests": null, "total_item_investigations": 1, "total_item_requests": 1, "unique_item_investigations": 1, "unique_item_requests": 1}, {"name": "Italy", "code": "IT", "title_requests": null, "total_item_investigations": 2, "total_item_requests": 2, "unique_item_investigations": 2, "unique_item_requests": 2}, {"name": "Philippines", "code": "PH", "title_requests": null, "total_item_investigations": 2, "total_item_requests": 2, "unique_item_investigations": 2, "unique_item_requests": 2}, {"name": "Taiwan", "code": "TW", "title_requests": null, "total_item_investigations": 1, "total_item_requests": 1, "unique_item_investigations": 1, "unique_item_requests": 1}, {"name": "United States", "code": "US", "title_requests": null, "total_item_investigations": 2, "total_item_requests": 2, "unique_item_investigations": 2, "unique_item_requests": 2}], "locations": [{"latitude": 14.6476, "longitude": 121.0494, "city": "Quezon City", "country_name": "Philippines", "country_code": "PH", "title_requests": null, "total_item_investigations": 1, "total_item_requests": 1, "unique_item_investigations": 1, "unique_item_requests": 1}, {"latitude": 14.7344, "longitude": 121.1425, "city": "Rodriguez", "country_name": "Philippines", "country_code": "PH", "title_requests": null, "total_item_investigations": 1, "total_item_requests": 1, "unique_item_investigations": 1, "unique_item_requests": 1}, {"latitude": 24.144, "longitude": 120.6844, "city": "Taichung", "country_name": "Taiwan", "country_code": "TW", "title_requests": null, "total_item_investigations": 1, "total_item_requests": 1, "unique_item_investigations": 1, "unique_item_requests": 1}, {"latitude": 37.7562, "longitude": -122.4866, "city": "San Francisco", "country_name": "United States", "country_code": "US", "title_requests": null, "total_item_investigations": 1, "total_item_requests": 1, "unique_item_investigations": 1, "unique_item_requests": 1}, {"latitude": 53.8554, "longitude": -1.5492, "city": "Leeds", "country_name": "United Kingdom", "country_code": "GB", "title_requests": null, "total_item_investigations": 4, "total_item_requests": 4, "unique_item_investigations": 2, "unique_item_requests": 2}, {"latitude": -34.5705, "longitude": -58.6269, "city": "Hurlingham", "country_name": "Argentina", "country_code": "AR", "title_requests": null, "total_item_investigations": 1, "total_item_requests": 1, "unique_item_investigations": 1, "unique_item_requests": 1}, {"latitude": -26.3975, "longitude": -54.6305, "city": "Puerto Eldorado", "country_name": "Argentina", "country_code": "AR", "title_requests": null, "total_item_investigations": 1, "total_item_requests": 1, "unique_item_investigations": 1, "unique_item_requests": 1}, {"latitude": 26.8756, "longitude": 80.9115, "city": "Lucknow", "country_name": "India", "country_code": "IN", "title_requests": null, "total_item_investigations": 1, "total_item_requests": 1, "unique_item_investigations": 1, "unique_item_requests": 1}, {"latitude": 32.1453, "longitude": -110.9456, "city": "Tucson", "country_name": "United States", "country_code": "US", "title_requests": null, "total_item_investigations": 1, "total_item_requests": 1, "unique_item_investigations": 1, "unique_item_requests": 1}, {"latitude": 46.1385, "longitude": 13.2226, "city": "Reana del Rojale", "country_name": "Italy", "country_code": "IT", "title_requests": null, "total_item_investigations": 1, "total_item_requests": 1, "unique_item_investigations": 1, "unique_item_requests": 1}, {"latitude": 50.406, "longitude": 4.4842, "city": "Montignies-sur-Sambre", "country_name": "Belgium", "country_code": "BE", "title_requests": null, "total_item_investigations": 1, "total_item_requests": 1, "unique_item_investigations": 1, "unique_item_requests": 1}, {"latitude": 43.4631, "longitude": 11.8783, "city": "Arezzo", "country_name": "Italy", "country_code": "IT", "title_requests": null, "total_item_investigations": 1, "total_item_requests": 1, "unique_item_investigations": 1, "unique_item_requests": 1}, {"latitude": 51.3235, "longitude": 12.4266, "city": "Leipzig", "country_name": "Germany", "country_code": "DE", "title_requests": null, "total_item_investigations": 1, "total_item_requests": 1, "unique_item_investigations": 1, "unique_item_requests": 1}], "version": "5", "release_date": "2021-01-01"}
{"proprietary_id": "irus:8892521", "URI": null, "DOI": "17.94184/192.9617439216201", "ISBN": "9781111111113", "book_title": "Worker laugh style meeting.", "grant": "grant", "grant_number": "grant number", "publisher": "Publisher Name", "begin_date": "2021-02-01", "end_date": "2021-02-28", "title_requests": 16, "total_item_investigations": null, "total_item_requests": null, "unique_item_investigations": null, "unique_item_requests": null, "country": [{"name": "Argentina", "code": "AR", "title_requests": null, "total_item_investigations": 2, "total_item_requests": 2, "unique_item_investigations": 2, "unique_item_requests": 2}, {"name": "Belgium", "code": "BE", "title_requests": null, "total_item_investigations": 1, "total_item_requests": 1, "unique_item_investigations": 1, "unique_item_requests": 1}, {"name": "Germany", "code": "DE", "title_requests": null, "total_item_investigations": 1, "total_item_requests": 1, "unique_item_investigations": 1, "unique_item_requests": 1}, {"name": "United Kingdom", "code": "GB", "title_requests": null, "total_item_investigations": 4, "total_item_requests": 4, "unique_item_investigations": 2, "unique_item_requests": 2}, {"name": "India", "code": "IN", "title_requests": null, "total_item_investigations": 1, "total_item_requests": 1, "unique_item_investigations": 1, "unique_item_requests": 1}, {"name": "Italy", "code": "IT", "title_requests": null, "total_item_investigations": 2, "total_item_requests": 2, "unique_item_investigations": 2, "unique_item_requests": 2}, {"name": "Philippines", "code": "PH", "title_requests": null, "total_item_investigations": 2, "total_item_requests": 2, "unique_item_investigations": 2, "unique_item_requests": 2}, {"name": "Taiwan", "code": "TW", "title_requests": null, "total_item_investigations": 1, "total_item_requests": 1, "unique_item_investigations": 1, "unique_item_requests": 1}, {"name": "United States", "code": "US", "title_requests": null, "total_item_investigations": 2, "total_item_requests": 2, "unique_item_investigations": 2, "unique_item_requests": 2}], "locations": [{"latitude": 14.6476, "longitude": 121.0494, "city": "Quezon City", "country_name": "Philippines", "country_code": "PH", "title_requests": null, "total_item_investigations": 1, "total_item_requests": 1, "unique_item_investigations": 1, "unique_item_requests": 1}, {"latitude": 14.7344, "longitude": 121.1425, "city": "Rodriguez", "country_name": "Philippines", "country_code": "PH", "title_requests": null, "total_item_investigations": 1, "total_item_requests": 1, "unique_item_investigations": 1, "unique_item_requests": 1}, {"latitude": 24.144, "longitude": 120.6844, "city": "Taichung", "country_name": "Taiwan", "country_code": "TW", "title_requests": null, "total_item_investigations": 1, "total_item_requests": 1, "unique_item_investigations": 1, "unique_item_requests": 1}, {"latitude": 37.7562, "longitude": -122.4866, "city": "San Francisco", "country_name": "United States", "country_code": "US", "title_requests": null, "total_item_investigations": 1, "total_item_requests": 1, "unique_item_investigations": 1, "unique_item_requests": 1}, {"latitude": 53.8554, "longitude": -1.5492, "city": "Leeds", "country_name": "United Kingdom", "country_code": "GB", "title_requests": null, "total_item_investigations": 4, "total_item_requests": 4, "unique_item_investigations": 2, "unique_item_requests": 2}, {"latitude": -34.5705, "longitude": -58.6269, "city": "Hurlingham", "country_name": "Argentina", "country_code": "AR", "title_requests": null, "total_item_investigations": 1, "total_item_requests": 1, "unique_item_investigations": 1, "unique_item_requests": 1}, {"latitude": -26.3975, "longitude": -54.6305, "city": "Puerto Eldorado", "country_name": "Argentina", "country_code": "AR", "title_requests": null, "total_item_investigations": 1, "total_item_requests": 1, "unique_item_investigations": 1, "unique_item_requests": 1}, {"latitude": 26.8756, "longitude": 80.9115, "city": "Lucknow", "country_name": "India", "country_code": "IN", "title_requests": null, "total_item_investigations": 1, "total_item_requests": 1, "unique_item_investigations": 1, "unique_item_requests": 1}, {"latitude": 32.1453, "longitude": -110.9456, "city": "Tucson", "country_name": "United States", "country_code": "US", "title_requests": null, "total_item_investigations": 1, "total_item_requests": 1, "unique_item_investigations": 1, "unique_item_requests": 1}, {"latitude": 46.1385, "longitude": 13.2226, "city": "Reana del Rojale", "country_name": "Italy", "country_code": "IT", "title_requests": null, "total_item_investigations": 1, "total_item_requests": 1, "unique_item_investigations": 1, "unique_item_requests": 1}, {"latitude": 50.406, "longitude": 4.4842, "city": "Montignies-sur-Sambre", "country_name": "Belgium", "country_code": "BE", "title_requests": null, "total_item_investigations": 1, "total_item_requests": 1, "unique_item_investigations": 1, "unique_item_requests": 1}, {"latitude": 43.4631, "longitude": 11.8783, "city": "Arezzo", "country_name": "Italy", "country_code": "IT", "title_requests": null, "total_item_investigations": 1, "total_item_requests": 1, "unique_item_investigations": 1, "unique_item_requests": 1}, {"latitude": 51.3235, "longitude": 12.4266, "city": "Leipzig", "country_name": "Germany", "country_code": "DE", "title_requests": null, "total_item_investigations": 1, "total_item_requests": 1, "unique_item_investigations": 1, "unique_item_requests": 1}], "version": "5", "release_date": "2021-01-01"}
